{"1": "glowstone_dust0",
"2": "orange_dye0",
"3": "orange_dye0",
"4": "gold_nugget1",
"5": "orange_dye2",
"6": "raw_iron2",
"7": "orange_dye2",
"8": "raw_iron1",
"9": "raw_iron0",
"10": "raw_iron0",
"11": "raw_iron0",
"12": "raw_iron0",
"13": "raw_iron0",
"14": "raw_iron0",
"15": "raw_iron0",
"16": "raw_iron0",
"17": "raw_iron0",
"18": "raw_iron0",
"19": "raw_iron0",
"20": "raw_iron0",
"21": "raw_iron0",
"22": "raw_iron0",
"23": "raw_iron1",
"24": "raw_iron1",
"25": "birch_wood0",
"26": "raw_iron1",
"27": "raw_iron0",
"28": "raw_iron0",
"29": "raw_iron1",
"30": "raw_iron1",
"31": "orange_dye1",
"32": "raw_iron1",
"33": "glowstone_dust0",
"34": "orange_dye0",
"35": "orange_dye0",
"36": "glowstone_dust2",
"37": "melon_seeds0",
"38": "melon_seeds0",
"39": "magma_cream1",
"40": "raw_iron1",
"41": "raw_iron0",
"42": "raw_iron0",
"43": "raw_iron0",
"44": "raw_iron0",
"45": "raw_iron0",
"46": "raw_iron0",
"47": "raw_iron0",
"48": "raw_iron0",
"49": "raw_iron0",
"50": "raw_iron0",
"51": "raw_iron0",
"52": "raw_iron0",
"53": "raw_iron0",
"54": "raw_iron0",
"55": "raw_iron1",
"56": "raw_iron2",
"57": "magma_cream2",
"58": "orange_dye2",
"59": "raw_iron0",
"60": "raw_iron0",
"61": "raw_iron0",
"62": "raw_iron2",
"63": "raw_iron0",
"64": "raw_iron1",
"65": "orange_dye0",
"66": "orange_dye0",
"67": "orange_dye0",
"68": "glowstone_dust2",
"69": "melon_seeds0",
"70": "melon_seeds0",
"71": "raw_iron1",
"72": "raw_iron0",
"73": "raw_iron0",
"74": "raw_iron0",
"75": "raw_iron0",
"76": "raw_iron0",
"77": "raw_iron0",
"78": "raw_iron0",
"79": "raw_iron0",
"80": "raw_iron0",
"81": "raw_iron0",
"82": "raw_iron0",
"83": "raw_iron0",
"84": "raw_iron0",
"85": "raw_iron0",
"86": "raw_iron1",
"87": "raw_iron1",
"88": "melon_seeds0",
"89": "melon_seeds0",
"90": "raw_iron2",
"91": "melon_seeds0",
"92": "raw_iron0",
"93": "raw_iron1",
"94": "raw_iron1",
"95": "raw_iron1",
"96": "raw_iron0",
"97": "orange_dye0",
"98": "orange_dye0",
"99": "orange_dye0",
"100": "glowstone_dust2",
"101": "magma_cream1",
"102": "melon_seeds0",
"103": "raw_iron1",
"104": "raw_iron0",
"105": "raw_iron0",
"106": "raw_iron0",
"107": "raw_iron0",
"108": "raw_iron0",
"109": "raw_iron0",
"110": "raw_iron0",
"111": "raw_iron0",
"112": "raw_iron0",
"113": "raw_iron0",
"114": "raw_iron0",
"115": "raw_iron0",
"116": "raw_iron1",
"117": "raw_iron0",
"118": "raw_iron1",
"119": "spider_eye0",
"120": "raw_iron1",
"121": "raw_iron2",
"122": "raw_iron2",
"123": "raw_iron2",
"124": "magma_cream2",
"125": "raw_iron0",
"126": "raw_iron0",
"127": "raw_iron0",
"128": "orange_dye2",
"129": "orange_dye0",
"130": "gold_nugget1",
"131": "orange_dye0",
"132": "orange_dye3",
"133": "birch_wood0",
"134": "magma_cream2",
"135": "raw_iron1",
"136": "raw_iron0",
"137": "raw_iron0",
"138": "raw_iron0",
"139": "raw_iron0",
"140": "raw_iron0",
"141": "raw_iron0",
"142": "raw_iron0",
"143": "raw_iron0",
"144": "raw_iron0",
"145": "raw_iron0",
"146": "raw_iron0",
"147": "raw_iron0",
"148": "raw_iron0",
"149": "melon_seeds0",
"150": "magma_cream1",
"151": "melon_seeds0",
"152": "melon_seeds0",
"153": "melon_seeds0",
"154": "melon_seeds0",
"155": "melon_seeds0",
"156": "melon_seeds0",
"157": "raw_iron0",
"158": "raw_iron0",
"159": "raw_iron0",
"160": "raw_iron0",
"161": "orange_dye0",
"162": "orange_dye0",
"163": "orange_dye0",
"164": "glowstone_dust2",
"165": "melon_seeds0",
"166": "orange_dye3",
"167": "raw_iron1",
"168": "raw_iron0",
"169": "raw_iron0",
"170": "raw_iron0",
"171": "raw_iron0",
"172": "raw_iron0",
"173": "raw_iron0",
"174": "raw_iron0",
"175": "raw_iron0",
"176": "raw_iron0",
"177": "raw_iron1",
"178": "raw_iron0",
"179": "raw_iron0",
"180": "orange_dye1",
"181": "melon_seeds0",
"182": "birch_wood0",
"183": "magma_cream1",
"184": "magma_cream1",
"185": "raw_iron1",
"186": "raw_iron1",
"187": "raw_iron1",
"188": "raw_iron1",
"189": "magma_cream1",
"190": "raw_iron0",
"191": "pumpkin_seeds0",
"192": "raw_iron0",
"193": "orange_dye0",
"194": "orange_dye0",
"195": "glowstone_dust2",
"196": "magma_cream1",
"197": "birch_wood0",
"198": "magma_cream2",
"199": "raw_iron0",
"200": "raw_iron0",
"201": "raw_iron0",
"202": "raw_iron0",
"203": "raw_iron0",
"204": "raw_iron0",
"205": "raw_iron0",
"206": "raw_iron0",
"207": "raw_iron0",
"208": "raw_iron0",
"209": "raw_iron1",
"210": "raw_iron0",
"211": "raw_iron1",
"212": "melon_seeds0",
"213": "birch_wood0",
"214": "orange_dye3",
"215": "magma_cream2",
"216": "raw_iron1",
"217": "raw_iron0",
"218": "raw_iron0",
"219": "raw_iron0",
"220": "raw_iron0",
"221": "raw_iron0",
"222": "orange_dye2",
"223": "pumpkin_seeds0",
"224": "raw_iron0",
"225": "orange_dye0",
"226": "orange_dye0",
"227": "orange_dye1",
"228": "melon_seeds0",
"229": "magma_cream1",
"230": "magma_cream1",
"231": "raw_iron1",
"232": "raw_iron0",
"233": "raw_iron0",
"234": "raw_iron0",
"235": "raw_iron0",
"236": "raw_iron0",
"237": "raw_iron1",
"238": "raw_iron0",
"239": "raw_iron0",
"240": "raw_iron0",
"241": "raw_iron1",
"242": "raw_iron2",
"243": "magma_cream1",
"244": "apple1",
"245": "magma_cream2",
"246": "melon_seeds1",
"247": "raw_iron1",
"248": "raw_iron0",
"249": "raw_iron0",
"250": "raw_iron0",
"251": "raw_iron0",
"252": "raw_iron0",
"253": "raw_iron0",
"254": "raw_iron1",
"255": "raw_iron0",
"256": "raw_iron0",
"257": "raw_iron1",
"258": "orange_dye1",
"259": "melon_seeds0",
"260": "melon_seeds0",
"261": "melon_seeds0",
"262": "orange_dye2",
"263": "raw_iron0",
"264": "raw_iron0",
"265": "raw_iron0",
"266": "raw_iron0",
"267": "raw_iron0",
"268": "raw_iron0",
"269": "orange_dye1",
"270": "raw_iron0",
"271": "raw_iron1",
"272": "raw_iron2",
"273": "magma_cream2",
"274": "magma_cream2",
"275": "magma_cream2",
"276": "melon_seeds0",
"277": "melon_seeds0",
"278": "raw_iron0",
"279": "raw_iron0",
"280": "raw_iron0",
"281": "raw_iron0",
"282": "raw_iron0",
"283": "orange_dye1",
"284": "raw_iron0",
"285": "raw_iron0",
"286": "raw_iron0",
"287": "orange_dye0",
"288": "raw_iron0",
"289": "orange_dye0",
"290": "orange_dye1",
"291": "melon_seeds0",
"292": "melon_seeds0",
"293": "magma_cream1",
"294": "magma_cream1",
"295": "raw_iron0",
"296": "raw_iron0",
"297": "raw_iron0",
"298": "raw_iron0",
"299": "raw_iron0",
"300": "raw_iron1",
"301": "raw_iron0",
"302": "raw_iron0",
"303": "raw_iron2",
"304": "crimson_nylium3",
"305": "birch_wood1",
"306": "melon_seeds1",
"307": "melon_seeds0",
"308": "raw_iron1",
"309": "raw_iron0",
"310": "raw_iron0",
"311": "raw_iron0",
"312": "raw_iron0",
"313": "raw_iron0",
"314": "raw_iron0",
"315": "orange_dye0",
"316": "raw_iron0",
"317": "raw_iron0",
"318": "raw_iron0",
"319": "raw_iron0",
"320": "orange_dye1",
"321": "raw_iron1",
"322": "melon_seeds0",
"323": "raw_iron2",
"324": "melon_seeds0",
"325": "melon_seeds0",
"326": "orange_dye3",
"327": "raw_iron1",
"328": "raw_iron0",
"329": "raw_iron0",
"330": "raw_iron0",
"331": "raw_iron0",
"332": "raw_iron0",
"333": "raw_iron0",
"334": "raw_iron1",
"335": "birch_wood1",
"336": "apple1",
"337": "birch_wood0",
"338": "melon_seeds0",
"339": "raw_iron2",
"340": "raw_iron0",
"341": "raw_iron0",
"342": "raw_iron0",
"343": "raw_iron0",
"344": "raw_iron0",
"345": "raw_iron0",
"346": "raw_iron0",
"347": "raw_iron1",
"348": "magma_cream2",
"349": "raw_iron0",
"350": "raw_iron0",
"351": "raw_iron0",
"352": "raw_iron0",
"353": "orange_dye1",
"354": "raw_iron1",
"355": "raw_iron2",
"356": "raw_iron2",
"357": "birch_wood0",
"358": "orange_dye3",
"359": "raw_iron1",
"360": "raw_iron0",
"361": "raw_iron0",
"362": "raw_iron0",
"363": "raw_iron0",
"364": "raw_iron0",
"365": "raw_iron0",
"366": "raw_iron1",
"367": "apple2",
"368": "magma_cream2",
"369": "magma_cream2",
"370": "apple2",
"371": "apple0",
"372": "raw_iron2",
"373": "raw_iron0",
"374": "raw_iron0",
"375": "raw_iron0",
"376": "raw_iron0",
"377": "raw_iron0",
"378": "raw_iron1",
"379": "raw_iron2",
"380": "spider_eye0",
"381": "raw_iron1",
"382": "raw_iron0",
"383": "raw_iron0",
"384": "raw_iron0",
"385": "raw_iron1",
"386": "raw_iron1",
"387": "raw_iron2",
"388": "orange_dye2",
"389": "magma_cream2",
"390": "orange_dye3",
"391": "raw_iron2",
"392": "raw_iron1",
"393": "raw_iron1",
"394": "raw_iron0",
"395": "raw_iron0",
"396": "raw_iron1",
"397": "raw_iron0",
"398": "raw_iron1",
"399": "magma_cream2",
"400": "magma_cream1",
"401": "magma_cream3",
"402": "melon_seeds1",
"403": "raw_iron1",
"404": "raw_iron1",
"405": "crimson_nylium2",
"406": "orange_dye0",
"407": "raw_iron0",
"408": "raw_iron0",
"409": "raw_iron0",
"410": "raw_iron0",
"411": "raw_iron1",
"412": "melon_seeds0",
"413": "magma_cream2",
"414": "raw_iron2",
"415": "raw_iron0",
"416": "raw_iron0",
"417": "raw_iron1",
"418": "raw_iron1",
"419": "raw_iron1",
"420": "melon_seeds0",
"421": "birch_wood0",
"422": "orange_dye3",
"423": "orange_dye2",
"424": "raw_iron2",
"425": "raw_iron1",
"426": "raw_iron1",
"427": "raw_iron0",
"428": "raw_iron0",
"429": "raw_iron0",
"430": "raw_iron1",
"431": "magma_cream1",
"432": "melon_seeds0",
"433": "magma_cream2",
"434": "melon_seeds0",
"435": "raw_iron1",
"436": "raw_iron1",
"437": "raw_iron1",
"438": "raw_iron0",
"439": "magma_cream0",
"440": "magma_cream0",
"441": "raw_iron0",
"442": "raw_iron1",
"443": "raw_iron2",
"444": "raw_iron2",
"445": "magma_cream2",
"446": "raw_iron2",
"447": "raw_iron1",
"448": "raw_iron1",
"449": "raw_iron1",
"450": "raw_iron1",
"451": "raw_iron1",
"452": "raw_iron1",
"453": "orange_dye3",
"454": "orange_dye3",
"455": "melon_seeds0",
"456": "raw_iron1",
"457": "raw_iron1",
"458": "raw_iron1",
"459": "raw_iron1",
"460": "raw_iron0",
"461": "raw_iron1",
"462": "melon_seeds0",
"463": "magma_cream1",
"464": "melon_seeds0",
"465": "raw_iron1",
"466": "melon_seeds0",
"467": "melon_seeds0",
"468": "raw_iron2",
"469": "raw_iron1",
"470": "raw_iron0",
"471": "raw_iron0",
"472": "orange_dye1",
"473": "magma_cream0",
"474": "magma_cream0",
"475": "raw_iron2",
"476": "melon_seeds0",
"477": "magma_cream2",
"478": "magma_cream3",
"479": "melon_seeds0",
"480": "birch_wood1",
"481": "raw_iron1",
"482": "raw_iron0",
"483": "raw_iron1",
"484": "raw_iron1",
"485": "birch_wood0",
"486": "magma_cream2",
"487": "magma_cream1",
"488": "raw_iron1",
"489": "raw_iron1",
"490": "melon_seeds0",
"491": "raw_iron1",
"492": "raw_iron0",
"493": "melon_seeds0",
"494": "raw_iron1",
"495": "magma_cream2",
"496": "raw_iron1",
"497": "raw_iron1",
"498": "magma_cream2",
"499": "raw_iron1",
"500": "raw_iron1",
"501": "magma_cream0",
"502": "raw_iron1",
"503": "raw_iron1",
"504": "raw_iron1",
"505": "raw_iron1",
"506": "raw_iron1",
"507": "magma_cream0",
"508": "apple0",
"509": "birch_wood1",
"510": "birch_wood1",
"511": "birch_wood1",
"512": "melon_seeds1",
"513": "raw_iron1",
"514": "raw_iron1",
"515": "raw_iron2",
"516": "melon_seeds0",
"517": "melon_seeds1",
"518": "magma_cream3",
"519": "melon_seeds0",
"520": "raw_iron1",
"521": "raw_iron1",
"522": "raw_iron1",
"523": "raw_iron1",
"524": "raw_iron0",
"525": "raw_iron1",
"526": "raw_iron1",
"527": "magma_cream0",
"528": "raw_iron1",
"529": "raw_iron0",
"530": "raw_iron0",
"531": "nether_wart1",
"532": "melon_seeds0",
"533": "magma_cream1",
"534": "raw_iron1",
"535": "raw_iron2",
"536": "melon_seeds0",
"537": "melon_seeds0",
"538": "melon_seeds0",
"539": "raw_iron1",
"540": "melon_seeds0",
"541": "birch_wood0",
"542": "orange_dye3",
"543": "apple0",
"544": "apple1",
"545": "raw_iron1",
"546": "raw_iron0",
"547": "raw_iron2",
"548": "melon_seeds1",
"549": "melon_seeds0",
"550": "magma_cream3",
"551": "birch_wood0",
"552": "raw_iron1",
"553": "raw_iron1",
"554": "raw_iron0",
"555": "raw_iron0",
"556": "raw_iron0",
"557": "raw_iron1",
"558": "raw_iron0",
"559": "magma_cream2",
"560": "raw_iron0",
"561": "raw_iron0",
"562": "raw_iron0",
"563": "melon_seeds0",
"564": "crimson_hyphae1",
"565": "magma_cream3",
"566": "raw_iron2",
"567": "melon_seeds0",
"568": "raw_iron0",
"569": "raw_iron1",
"570": "magma_cream1",
"571": "melon_seeds0",
"572": "crimson_nylium2",
"573": "melon_seeds0",
"574": "melon_seeds0",
"575": "spider_eye1",
"576": "melon_seeds0",
"577": "raw_iron1",
"578": "pumpkin_seeds2",
"579": "melon_seeds0",
"580": "melon_seeds0",
"581": "birch_wood1",
"582": "magma_cream3",
"583": "birch_wood2",
"584": "melon_seeds0",
"585": "raw_iron1",
"586": "raw_iron0",
"587": "raw_iron0",
"588": "raw_iron0",
"589": "raw_iron0",
"590": "raw_iron0",
"591": "magma_cream0",
"592": "raw_iron0",
"593": "raw_iron0",
"594": "raw_iron0",
"595": "raw_iron0",
"596": "raw_iron0",
"597": "orange_dye3",
"598": "magma_cream3",
"599": "apple3",
"600": "raw_iron2",
"601": "melon_seeds1",
"602": "melon_seeds0",
"603": "raw_iron1",
"604": "melon_seeds0",
"605": "melon_seeds0",
"606": "melon_seeds0",
"607": "magma_cream1",
"608": "melon_seeds0",
"609": "raw_iron0",
"610": "raw_iron2",
"611": "melon_seeds0",
"612": "melon_seeds0",
"613": "melon_seeds1",
"614": "apple3",
"615": "magma_cream3",
"616": "birch_wood1",
"617": "raw_iron1",
"618": "raw_iron1",
"619": "raw_iron1",
"620": "raw_iron0",
"621": "raw_iron1",
"622": "raw_iron0",
"623": "magma_cream0",
"624": "raw_iron0",
"625": "raw_iron0",
"626": "raw_iron0",
"627": "raw_iron0",
"628": "raw_iron1",
"629": "melon_seeds0",
"630": "raw_iron1",
"631": "glowstone_dust3",
"632": "magma_cream3",
"633": "magma_cream3",
"634": "magma_cream3",
"635": "melon_seeds0",
"636": "melon_seeds0",
"637": "raw_iron1",
"638": "raw_iron2",
"639": "birch_wood0",
"640": "raw_iron2",
"641": "raw_iron1",
"642": "raw_iron2",
"643": "melon_seeds0",
"644": "raw_iron1",
"645": "birch_wood0",
"646": "magma_cream3",
"647": "apple3",
"648": "birch_wood2",
"649": "raw_iron2",
"650": "raw_iron1",
"651": "raw_iron1",
"652": "raw_iron0",
"653": "raw_iron0",
"654": "raw_iron0",
"655": "magma_cream0",
"656": "raw_iron0",
"657": "raw_iron0",
"658": "raw_iron0",
"659": "raw_iron0",
"660": "raw_iron1",
"661": "orange_dye1",
"662": "melon_seeds0",
"663": "raw_iron1",
"664": "melon_seeds0",
"665": "birch_wood0",
"666": "magma_cream3",
"667": "magma_cream3",
"668": "crimson_hyphae2",
"669": "birch_wood2",
"670": "crimson_hyphae2",
"671": "apple3",
"672": "birch_wood2",
"673": "raw_iron0",
"674": "raw_iron1",
"675": "raw_iron2",
"676": "melon_seeds0",
"677": "birch_wood0",
"678": "magma_cream3",
"679": "magma_cream3",
"680": "podzol0",
"681": "raw_iron1",
"682": "raw_iron1",
"683": "orange_dye1",
"684": "raw_iron0",
"685": "raw_iron1",
"686": "raw_iron0",
"687": "orange_dye0",
"688": "raw_iron0",
"689": "raw_iron0",
"690": "raw_iron0",
"691": "raw_iron0",
"692": "raw_iron0",
"693": "raw_iron0",
"694": "magma_cream0",
"695": "melon_seeds0",
"696": "orange_dye3",
"697": "raw_iron2",
"698": "raw_iron1",
"699": "birch_wood0",
"700": "melon_seeds1",
"701": "birch_wood2",
"702": "apple3",
"703": "birch_wood1",
"704": "raw_iron2",
"705": "raw_iron0",
"706": "raw_iron0",
"707": "raw_iron1",
"708": "melon_seeds0",
"709": "birch_wood0",
"710": "melon_seeds2",
"711": "cocoa_beans1",
"712": "cocoa_beans1",
"713": "birch_wood2",
"714": "melon_seeds0",
"715": "raw_iron1",
"716": "raw_iron0",
"717": "raw_iron0",
"718": "raw_iron0",
"719": "orange_dye0",
"720": "raw_iron0",
"721": "raw_iron0",
"722": "raw_iron0",
"723": "raw_iron0",
"724": "raw_iron0",
"725": "raw_iron0",
"726": "raw_iron0",
"727": "raw_iron1",
"728": "raw_iron1",
"729": "raw_iron1",
"730": "raw_iron2",
"731": "crimson_nylium2",
"732": "raw_iron1",
"733": "magma_cream1",
"734": "raw_iron1",
"735": "spider_eye0",
"736": "raw_iron2",
"737": "raw_iron0",
"738": "raw_iron1",
"739": "raw_iron2",
"740": "raw_iron2",
"741": "birch_wood1",
"742": "magma_cream3",
"743": "cocoa_beans1",
"744": "cocoa_beans0",
"745": "melon_seeds2",
"746": "apple1",
"747": "melon_seeds0",
"748": "raw_iron0",
"749": "raw_iron1",
"750": "raw_iron0",
"751": "orange_dye0",
"752": "raw_iron0",
"753": "raw_iron0",
"754": "raw_iron0",
"755": "raw_iron0",
"756": "raw_iron0",
"757": "raw_iron0",
"758": "raw_iron1",
"759": "raw_iron1",
"760": "raw_iron1",
"761": "raw_iron1",
"762": "raw_iron1",
"763": "raw_iron1",
"764": "raw_iron1",
"765": "raw_iron1",
"766": "raw_iron1",
"767": "spider_eye0",
"768": "raw_iron1",
"769": "raw_iron1",
"770": "raw_iron1",
"771": "melon_seeds0",
"772": "raw_iron2",
"773": "melon_seeds1",
"774": "birch_wood2",
"775": "birch_wood2",
"776": "melon_seeds2",
"777": "magma_cream3",
"778": "birch_wood2",
"779": "raw_iron2",
"780": "melon_seeds0",
"781": "raw_iron1",
"782": "raw_iron0",
"783": "raw_iron1",
"784": "raw_iron0",
"785": "raw_iron0",
"786": "raw_iron0",
"787": "raw_iron0",
"788": "raw_iron0",
"789": "raw_iron0",
"790": "raw_iron0",
"791": "orange_dye1",
"792": "magma_cream0",
"793": "raw_iron1",
"794": "raw_iron1",
"795": "melon_seeds0",
"796": "raw_iron1",
"797": "raw_iron0",
"798": "raw_iron0",
"799": "raw_iron1",
"800": "raw_iron1",
"801": "raw_iron0",
"802": "raw_iron1",
"803": "melon_seeds0",
"804": "melon_seeds0",
"805": "birch_wood0",
"806": "magma_cream2",
"807": "birch_wood1",
"808": "melon_seeds1",
"809": "melon_seeds2",
"810": "birch_wood1",
"811": "magma_cream2",
"812": "melon_seeds0",
"813": "raw_iron1",
"814": "magma_cream1",
"815": "raw_iron0",
"816": "raw_iron0",
"817": "raw_iron0",
"818": "raw_iron0",
"819": "raw_iron0",
"820": "raw_iron0",
"821": "raw_iron0",
"822": "raw_iron0",
"823": "raw_iron1",
"824": "spider_eye0",
"825": "melon_seeds0",
"826": "melon_seeds0",
"827": "orange_dye1",
"828": "raw_iron1",
"829": "orange_dye0",
"830": "orange_dye0",
"831": "magma_cream0",
"832": "magma_cream0",
"833": "raw_iron1",
"834": "raw_iron1",
"835": "melon_seeds0",
"836": "melon_seeds0",
"837": "birch_wood0",
"838": "melon_seeds0",
"839": "magma_cream3",
"840": "birch_wood1",
"841": "birch_wood0",
"842": "orange_dye3",
"843": "melon_seeds1",
"844": "birch_wood0",
"845": "raw_iron1",
"846": "magma_cream1",
"847": "orange_dye0",
"848": "raw_iron0",
"849": "raw_iron0",
"850": "raw_iron0",
"851": "raw_iron0",
"852": "raw_iron0",
"853": "raw_iron0",
"854": "raw_iron1",
"855": "raw_iron1",
"856": "melon_seeds0",
"857": "apple2",
"858": "orange_dye3",
"859": "apple2",
"860": "birch_wood1",
"861": "orange_dye3",
"862": "birch_wood0",
"863": "melon_seeds1",
"864": "melon_seeds2",
"865": "raw_iron0",
"866": "raw_iron1",
"867": "melon_seeds0",
"868": "melon_seeds0",
"869": "melon_seeds0",
"870": "birch_wood0",
"871": "magma_cream3",
"872": "magma_cream3",
"873": "birch_wood1",
"874": "melon_seeds0",
"875": "melon_seeds0",
"876": "magma_cream3",
"877": "raw_iron2",
"878": "melon_seeds0",
"879": "raw_iron1",
"880": "raw_iron0",
"881": "raw_iron0",
"882": "raw_iron0",
"883": "raw_iron0",
"884": "raw_iron0",
"885": "raw_iron0",
"886": "raw_iron1",
"887": "raw_iron1",
"888": "birch_wood0",
"889": "birch_wood0",
"890": "birch_wood0",
"891": "orange_dye3",
"892": "birch_wood1",
"893": "birch_wood1",
"894": "magma_cream3",
"895": "birch_wood1",
"896": "melon_seeds1",
"897": "raw_iron0",
"898": "raw_iron1",
"899": "raw_iron1",
"900": "melon_seeds0",
"901": "melon_seeds0",
"902": "birch_wood0",
"903": "magma_cream3",
"904": "magma_cream3",
"905": "melon_seeds1",
"906": "raw_iron2",
"907": "melon_seeds0",
"908": "magma_cream1",
"909": "magma_cream2",
"910": "birch_wood0",
"911": "melon_seeds0",
"912": "raw_iron1",
"913": "raw_iron0",
"914": "raw_iron0",
"915": "raw_iron0",
"916": "raw_iron0",
"917": "raw_iron0",
"918": "raw_iron0",
"919": "raw_iron0",
"920": "raw_iron0",
"921": "raw_iron1",
"922": "orange_dye1",
"923": "raw_iron1",
"924": "magma_cream0",
"925": "melon_seeds0",
"926": "birch_wood0",
"927": "melon_seeds1",
"928": "melon_seeds1",
"929": "raw_iron1",
"930": "raw_iron1",
"931": "raw_iron1",
"932": "raw_iron2",
"933": "melon_seeds0",
"934": "magma_cream1",
"935": "magma_cream3",
"936": "birch_wood0",
"937": "magma_cream1",
"938": "melon_seeds0",
"939": "raw_iron1",
"940": "orange_dye2",
"941": "magma_cream2",
"942": "magma_cream3",
"943": "magma_cream1",
"944": "orange_dye1",
"945": "raw_iron0",
"946": "raw_iron0",
"947": "raw_iron0",
"948": "raw_iron0",
"949": "raw_iron0",
"950": "raw_iron0",
"951": "raw_iron0",
"952": "raw_iron0",
"953": "raw_iron0",
"954": "raw_iron0",
"955": "raw_iron0",
"956": "raw_iron1",
"957": "melon_seeds0",
"958": "melon_seeds0",
"959": "melon_seeds1",
"960": "melon_seeds1",
"961": "raw_iron0",
"962": "pumpkin_seeds2",
"963": "melon_seeds0",
"964": "melon_seeds0",
"965": "melon_seeds0",
"966": "melon_seeds0",
"967": "magma_cream2",
"968": "magma_cream2",
"969": "birch_wood0",
"970": "raw_iron2",
"971": "raw_iron1",
"972": "raw_iron1",
"973": "magma_cream2",
"974": "magma_cream2",
"975": "magma_cream3",
"976": "melon_seeds1",
"977": "raw_iron1",
"978": "raw_iron0",
"979": "raw_iron0",
"980": "raw_iron0",
"981": "raw_iron0",
"982": "raw_iron0",
"983": "raw_iron0",
"984": "raw_iron0",
"985": "raw_iron0",
"986": "raw_iron0",
"987": "raw_iron0",
"988": "raw_iron0",
"989": "raw_iron0",
"990": "raw_iron1",
"991": "apple0",
"992": "melon_seeds0",
"993": "raw_iron1",
"994": "raw_iron1",
"995": "melon_seeds0",
"996": "melon_seeds1",
"997": "orange_dye2",
"998": "birch_wood0",
"999": "birch_wood0",
"1000": "magma_cream3",
"1001": "magma_cream2",
"1002": "melon_seeds0",
"1003": "raw_iron1",
"1004": "raw_iron1",
"1005": "melon_seeds1",
"1006": "magma_cream2",
"1007": "magma_cream2",
"1008": "magma_cream3",
"1009": "magma_cream2",
"1010": "raw_iron0",
"1011": "raw_iron0",
"1012": "raw_iron0",
"1013": "raw_iron0",
"1014": "raw_iron0",
"1015": "raw_iron0",
"1016": "raw_iron0",
"1017": "raw_iron0",
"1018": "raw_iron0",
"1019": "raw_iron0",
"1020": "raw_iron0",
"1021": "raw_iron0",
"1022": "raw_iron1",
"1023": "melon_seeds0",
"1024": "melon_seeds0"}